{
  "todo": [
    {
      "activity": "Eat",
      "id": 1,
      "done": true
    },
    {
      "activity": "Sleep",
      "id": 2
    },
    {
      "activity": "Code",
      "id": 3
    },
    {
      "activity": "Repeat",
      "id": 4
    },
    {
      "activity": "3",
      "id": 5
    },
    {
      "activity": "test",
      "id": 6
    },
    {
      "activity": "",
      "id": 7
    },
    {
      "activity": "dw",
      "id": 8,
      "done": true
    },
    {
      "activity": "ry",
      "done": true,
      "id": 9
    },
    {
      "activity": "dw",
      "done": false,
      "id": 10
    },
    {
      "activity": "ddd",
      "done": false,
      "id": 11
    },
    {
      "activity": "test",
      "done": false,
      "id": 12
    },
    {
      "activity": "another test",
      "done": false,
      "id": 13
    },
    {
      "activity": "at",
      "done": false,
      "id": 14
    },
    {
      "activity": "at",
      "done": false,
      "id": 15
    },
    {
      "activity": "111",
      "done": false,
      "id": 16
    },
    {
      "activity": "444",
      "done": false,
      "id": 17
    },
    {
      "activity": "wawa",
      "done": false,
      "id": 18
    },
    {
      "activity": "ddd",
      "done": false,
      "id": 19
    },
    {
      "activity": "test REDUXXXX",
      "done": false,
      "id": 20
    },
    {
      "activity": "test REDUXXXX",
      "done": false,
      "id": 21
    },
    {
      "activity": "redux thunk",
      "done": false,
      "id": 22
    },
    {
      "activity": "redux thunk",
      "done": false,
      "id": 23
    },
    {
      "activity": "redux thunk",
      "done": false,
      "id": 24
    },
    {
      "activity": "test redux thunk",
      "done": false,
      "id": 25
    },
    {
      "activity": "r",
      "done": false,
      "id": 26
    },
    {
      "activity": "r",
      "done": false,
      "id": 27
    },
    {
      "activity": "why error",
      "done": false,
      "id": 28
    },
    {
      "activity": "why error",
      "done": false,
      "id": 29
    },
    {
      "activity": "test",
      "done": false,
      "id": 30
    },
    {
      "activity": "pst",
      "done": false,
      "id": 31
    },
    {
      "activity": "p",
      "done": false,
      "id": 32
    },
    {
      "activity": "test",
      "done": false,
      "id": 33
    }
  ]
}